ceja/__init__.py
ceja/functions.py
ceja-0.4.0.dist-info/WHEEL
ceja-0.4.0.dist-info/METADATA
ceja-0.4.0.dist-info/RECORD
